LICENSE
MANIFEST.in
compose_x_render/__init__.py
compose_x_render/cli.py
compose_x_render/compose-spec.json
compose_x_render/compose_x_render.py
compose_x_render/consts.py
compose_x_render/envsubst.py
compose_x_render/list_management.py
compose_x_render/networking.py
compose_x_render-1.1.0.dist-info/LICENSE
compose_x_render-1.1.0.dist-info/METADATA
compose_x_render-1.1.0.dist-info/WHEEL
compose_x_render-1.1.0.dist-info/entry_points.txt
compose_x_render-1.1.0.dist-info/RECORD
